colorclip/__init__.py
colorclip/colorclip.py
colorclip-1.0.6.dist-info/LICENSE
colorclip-1.0.6.dist-info/METADATA
colorclip-1.0.6.dist-info/WHEEL
colorclip-1.0.6.dist-info/top_level.txt
colorclip-1.0.6.dist-info/RECORD
