Metadata-Version: 2.1
Name: colorclip
Version: 1.0.6
Summary: A Python color pack library
Home-page: https://t.me/Onefinalhug
Download-URL: https://github.com/lillisfeb/colorclip
Author: Bevlil
Author-email: voidlillis@gmail.com
License: MIT
Keywords: color pack library,python terminal console
Classifier: Programming Language :: Python :: 3
Classifier: License :: OSI Approved :: MIT License
Classifier: Operating System :: OS Independent
License-File: LICENSE
